evalica-0.3.2.dist-info/METADATA
evalica-0.3.2.dist-info/WHEEL
evalica-0.3.2.dist-info/entry_points.txt
evalica-0.3.2.dist-info/licenses/LICENSE
evalica/__init__.py
evalica/naive.py
evalica/gradio/__main__.py
evalica/test_evalica.py
evalica/py.typed
evalica/evalica.pyi
evalica/__main__.py
evalica/evalica.abi3.so
evalica-0.3.2.dist-info/RECORD
