Metadata-Version: 2.4
Name: evalica
Version: 0.3.2
Classifier: Development Status :: 4 - Beta
Classifier: Intended Audience :: Developers
Classifier: Intended Audience :: Science/Research
Classifier: License :: OSI Approved :: Apache Software License
Classifier: Programming Language :: Rust
Classifier: Programming Language :: Python :: Implementation :: CPython
Classifier: Programming Language :: Python :: Implementation :: PyPy
Classifier: Topic :: Scientific/Engineering :: Artificial Intelligence
Classifier: Topic :: Scientific/Engineering :: Information Analysis
Classifier: Typing :: Typed
Requires-Dist: numpy >=1.16.0
Requires-Dist: pandas
Requires-Dist: abi3audit ; extra == 'dev'
Requires-Dist: hypothesis[numpy] ; extra == 'dev'
Requires-Dist: mypy ; extra == 'dev'
Requires-Dist: nbqa ; extra == 'dev'
Requires-Dist: notebook ; extra == 'dev'
Requires-Dist: pandas-stubs ; extra == 'dev'
Requires-Dist: plotly ; extra == 'dev'
Requires-Dist: pytest ; extra == 'dev'
Requires-Dist: pytest-codspeed ; extra == 'dev'
Requires-Dist: pytest-cov ; extra == 'dev'
Requires-Dist: ruff ; extra == 'dev'
Requires-Dist: twine ; extra == 'dev'
Requires-Dist: mkdocs ; extra == 'docs'
Requires-Dist: mkdocs-material ; extra == 'docs'
Requires-Dist: mkdocstrings-python ; extra == 'docs'
Requires-Dist: gradio ; extra == 'gradio'
Requires-Dist: plotly ; extra == 'gradio'
Provides-Extra: dev
Provides-Extra: docs
Provides-Extra: gradio
License-File: LICENSE
Summary: Evalica, your favourite evaluation toolkit.
Keywords: Bradley-Terry,Elo,PageRank,eigenvector,evaluation,leaderboard,pairwise comparisons,ranking,rating,statistics
License: Apache-2.0
Requires-Python: ~=3.8
Project-URL: Homepage, https://github.com/dustalov/evalica
Project-URL: Changelog, https://github.com/dustalov/evalica/releases
Project-URL: Issues, https://github.com/dustalov/evalica/issues
Project-URL: Documentation, https://evalica.readthedocs.io/
Project-URL: Download, https://pypi.org/project/evalica/#files
Project-URL: Repository, https://github.com/dustalov/evalica
